kennitala/__init__.py
kennitala-0.2.0.dist-info/licenses/LICENSE
kennitala-0.2.0.dist-info/METADATA
kennitala-0.2.0.dist-info/WHEEL
kennitala-0.2.0.dist-info/top_level.txt
kennitala-0.2.0.dist-info/RECORD
