Metadata-Version: 2.4
Name: kennitala
Version: 0.2.0
Summary: Icelandic national registry codes made easy
Home-page: https://github.com/ojake/python-kennitala
Author: Sævar Öfjörð Magnússon, Jakub Owczarski
Author-email: hallo@overcast.is
License: MIT license
Classifier: Development Status :: 4 - Beta
Classifier: Intended Audience :: Developers
Classifier: Programming Language :: Python :: 3
License-File: LICENSE
Dynamic: author
Dynamic: author-email
Dynamic: classifier
Dynamic: description
Dynamic: home-page
Dynamic: license
Dynamic: license-file
Dynamic: summary
